xbtool/__init__.py
xbtool/xb.py
xbtool-0.0.4.dist-info/METADATA
xbtool-0.0.4.dist-info/WHEEL
xbtool-0.0.4.dist-info/top_level.txt
xbtool-0.0.4.dist-info/RECORD
