Metadata-Version: 2.1
Name: xbtool
Version: 0.0.4
Summary: A library of your own tools
Author: XiangBing
Author-email: 2677506404@qq.com
License: MIT
Requires-Python: >=3.8
Requires-Dist: pyodbc
Requires-Dist: numpy
Requires-Dist: pandas
